django_restframework_2fa/__init__.py
django_restframework_2fa/apps.py
django_restframework_2fa/models.py
django_restframework_2fa/serializers.py
django_restframework_2fa/services.py
django_restframework_2fa/tests.py
django_restframework_2fa/urls.py
django_restframework_2fa/views.py
django_restframework_2fa/migrations/0001_initial.py
django_restframework_2fa/migrations/__init__.py
django_restframework_2fa-0.0.16.dist-info/LICENSE
django_restframework_2fa-0.0.16.dist-info/METADATA
django_restframework_2fa-0.0.16.dist-info/WHEEL
django_restframework_2fa-0.0.16.dist-info/top_level.txt
django_restframework_2fa-0.0.16.dist-info/RECORD
