Metadata-Version: 2.1
Name: django-restframework-2fa
Version: 0.0.16
Summary: A simple two factor authentication plugin for DRF compatible to work with Twilio's SMS service..
Home-page: https://github.com/jeetpatel9/django-restframework-2fa.git
Author: Jeet Patel
Author-email: jpatel99967@gmail.com
License: UNKNOWN
Platform: UNKNOWN
Classifier: Environment :: Web Environment
Classifier: Programming Language :: Python
Classifier: Programming Language :: Python :: 3
Classifier: Programming Language :: Python :: 3.6
Classifier: Programming Language :: Python :: 3.7
Classifier: Framework :: Django
Classifier: Framework :: Django :: 3.1
Classifier: Framework :: Django :: 3.2
Classifier: Intended Audience :: Developers
Classifier: License :: OSI Approved :: MIT License
Classifier: Operating System :: OS Independent
Classifier: Topic :: Internet :: WWW/HTTP
Requires-Python: >=3.7
Requires-Dist: djangorestframework (==3.12.4)
Requires-Dist: django (==3.2.4)
Requires-Dist: twilio (==6.55.0)
Requires-Dist: djangorestframework-simplejwt (==4.6.0)
